dpp_common_utils/__init__.py
dpp_common_utils/path.py
dpp_common_utils/selenium.py
dpp_common_utils/string.py
dpp_common_utils/timestamp.py
dpp_common_utils-0.2.0.dist-info/LICENSE
dpp_common_utils-0.2.0.dist-info/METADATA
dpp_common_utils-0.2.0.dist-info/WHEEL
dpp_common_utils-0.2.0.dist-info/top_level.txt
dpp_common_utils-0.2.0.dist-info/RECORD
