Metadata-Version: 2.1
Name: dpp-common-utils
Version: 0.2.0
Summary: A small utils package
Home-page: https://git.uni-due.de/
Author: J. Hohenstein
Author-email: j.hoh@t-online.de
License: UNKNOWN
Platform: UNKNOWN
Classifier: Programming Language :: Python :: 3
Classifier: License :: OSI Approved :: MIT License
Classifier: Operating System :: OS Independent
Requires-Python: >=3.7
Requires-Dist: selenium (~=3.141.0)
Requires-Dist: chromedriver-binary (~=83.0.4103.39.0)
